tenex_cli/__init__.py
tenex_cli/cli.py
tenex_cli/codex.py
tenex_cli/config.py
tenex_cli/editor.py
tenex_cli/logger.py
tenex_cli/prompts.py
tenex_cli/runtime.py
tenex_cli/session.py
tenex_cli/tmux.py
tenex_cli/workflows.py
tenex_cli-0.1.0.dist-info/METADATA
tenex_cli-0.1.0.dist-info/WHEEL
tenex_cli-0.1.0.dist-info/entry_points.txt
tenex_cli-0.1.0.dist-info/licenses/LICENSE
tenex_cli-0.1.0.dist-info/RECORD
