Metadata-Version: 2.4
Name: tenex-cli
Version: 0.1.0
Summary: Easily control swarms of agents
Project-URL: Homepage, https://github.com/Mockapapella/tenex
Author-email: Quinten <quinten.lisowe@thelisowe.com>
License: Apache-2.0
License-File: LICENSE
Keywords: automation,cli,codex,tmux
Classifier: License :: OSI Approved :: Apache Software License
Classifier: Operating System :: POSIX
Classifier: Programming Language :: Python :: 3
Requires-Python: >=3.10
Requires-Dist: click<8.2,>=8.1
Requires-Dist: rich>=13.8.0
Requires-Dist: typer>=0.12.5
